fromage/__init__.py
fromage/io/__init__.py
fromage/io/edit_file.py
fromage/io/parse_config_file.py
fromage/io/read_file.py
fromage/scripts/__init__.py
fromage/scripts/fro_assign_charges.py
fromage/scripts/fro_coupling.py
fromage/scripts/fro_dimer_tools.py
fromage/scripts/fro_exciton_classification.py
fromage/scripts/fro_pick_mol.py
fromage/scripts/fro_pop_stat.py
fromage/scripts/fro_prep_run.py
fromage/scripts/fro_run.py
fromage/scripts/fro_uc_tools.py
fromage/scripts/fro_volumetrics.py
fromage/utils/__init__.py
fromage/utils/atom.py
fromage/utils/calc.py
fromage/utils/dimer.py
fromage/utils/fit.py
fromage/utils/handle_atoms.py
fromage/utils/per_table.py
fromage/utils/run_sequence.py
fromage/utils/volume.py
fromage/utils/array_operations/__init__.py
fromage/utils/array_operations/_matrix.py
fromage/utils/array_operations/_planes.py
fromage/utils/exci_coupling/CATC.py
fromage/utils/exci_coupling/PDA.py
fromage/utils/exci_coupling/__init__.py
fromage/utils/exci_coupling/diabatize.py
fromage/utils/exci_coupling/elements.py
fromage/utils/exci_coupling/read_g09.py
fromage/utils/exci_coupling/xyz.py
fromage/utils/mol/__init__.py
fromage/utils/mol/_bonding.py
fromage/utils/mol/_cell_operations.py
fromage/utils/mol/_char.py
fromage/utils/mol/_geom.py
fromage/utils/mol/_listyness.py
fromage/utils/mol/_selecting.py
fromage-1.1.data/scripts/fro_assign_charges.py
fromage-1.1.data/scripts/fro_coupling.py
fromage-1.1.data/scripts/fro_dimer_tools.py
fromage-1.1.data/scripts/fro_exciton_classification.py
fromage-1.1.data/scripts/fro_pick_mol.py
fromage-1.1.data/scripts/fro_pop_stat.py
fromage-1.1.data/scripts/fro_prep_run.py
fromage-1.1.data/scripts/fro_run.py
fromage-1.1.data/scripts/fro_uc_tools.py
fromage-1.1.data/scripts/fro_volumetrics.py
fromage-1.1.dist-info/LICENSE
fromage-1.1.dist-info/METADATA
fromage-1.1.dist-info/WHEEL
fromage-1.1.dist-info/top_level.txt
fromage-1.1.dist-info/RECORD
